[{"tweet_id":"1590455096067981313","screen_name":"FrenzyCapital","user_name":"Frenzy Cap","full_text":"Trending: Retail\n\n$RL -5.16 %\n$TPR -3.28 %\n$KMX -0.17 %\n$CPRI -4.41 %\n$WMT -1.90 %\n$LULU -2.22 %\n$KR 1.89 %\n$HD -1.51 %\n$IAA -2.81 %\n$CVNA 2.99 %\n\nhttps://t.co/WV3qS0l6fi","sentiment":"neu","source":"<a href=\"http://www.jpfurtak.com:8080\" rel=\"nofollow\">trendingtickers2</a>","create_at":"Wed Nov 09 21:23:38 +0000 2022"},{"tweet_id":"1590389603973955584","screen_name":"FrenzyCapital","user_name":"Frenzy Cap","full_text":"Trending: Retail\n\n$KMX -1.91 %\n$KR 2.70 %\n$WMT -1.17 %\n$HD -0.18 %\n$IAA 1.57 %\n$SFM 11.79 %\n$SBH -0.89 %\n$BBBY -7.76 %\n$CVNA 3.87 %\n$CPRI 0.89 %\n\nhttps://t.co/WV3qS0l6fi","sentiment":"neu","source":"<a href=\"http://www.jpfurtak.com:8080\" rel=\"nofollow\">trendingtickers2</a>","create_at":"Wed Nov 09 17:03:24 +0000 2022"},{"tweet_id":"1590384599003467777","screen_name":"FrenzyCapital","user_name":"Frenzy Cap","full_text":"Trending: Retail\n\n$KMX -2.00 %\n$KR 2.87 %\n$WMT -1.16 %\n$HD -0.09 %\n$SBH -0.78 %\n$IAA 1.26 %\n$SFM 11.72 %\n$BBBY -8.50 %\n$CVNA 0.48 %\n$CPRI 1.41 %\n\nhttps://t.co/WV3qS0lE4Q","sentiment":"neu","source":"<a href=\"http://www.jpfurtak.com:8080\" rel=\"nofollow\">trendingtickers2</a>","create_at":"Wed Nov 09 16:43:30 +0000 2022"}]
