[{"tweet_id":"1505348001023217665","screen_name":"Hawko_44","user_name":"ze reflectorz $MRI (🥊,🐶)","full_text":"$MRI $HWI $HEAL","sentiment":"neu","source":"<a href=\"http://twitter.com/download/iphone\" rel=\"nofollow\">Twitter for iPhone</a>","create_at":"Sun Mar 20 00:58:26 +0000 2022"},{"tweet_id":"1505130780238008328","screen_name":"AdalKha07203482","user_name":"Adal Khan","full_text":"@ksicrypto $hwi $heal $qnt","sentiment":"neu","source":"<a href=\"http://twitter.com/download/iphone\" rel=\"nofollow\">Twitter for iPhone</a>","create_at":"Sat Mar 19 10:35:16 +0000 2022"}]
