[{"tweet_id":"1594169913232556032","screen_name":"ApaxxR","user_name":"#APAXX Roofing","full_text":"Flaming Star Nebula  https://t.co/Iji1nEEKnC \n\nht @NASA \n#SaturdayThoughts #SaturdayMotivation \n#astronomy #photography #inspiration #APAXX \n\n📷 Adam Block https://t.co/fm1nUkJ4hp","sentiment":"pos","source":"<a href=\"https://about.twitter.com/products/tweetdeck\" rel=\"nofollow\">TweetDeck</a>","create_at":"Sun Nov 20 03:25:00 +0000 2022"},{"tweet_id":"1594119304995168256","screen_name":"FredyRojer","user_name":"fredzy","full_text":"@NASA L r T m n T X","sentiment":"neu","source":"<a href=\"http://twitter.com/download/android\" rel=\"nofollow\">Twitter for Android</a>","create_at":"Sun Nov 20 00:03:54 +0000 2022"},{"tweet_id":"1594025102878081024","screen_name":"cybermania2020","user_name":"Chippytea","full_text":"@DobbersW @NASA Yoyo eh.","sentiment":"neu","source":"<a href=\"http://twitter.com/download/android\" rel=\"nofollow\">Twitter for Android</a>","create_at":"Sat Nov 19 17:49:34 +0000 2022"},{"tweet_id":"1594011544156774400","screen_name":"nolangoldie","user_name":"Nolan Goldie","full_text":"@NASA Uranus","sentiment":"neu","source":"<a href=\"http://twitter.com/download/iphone\" rel=\"nofollow\">Twitter for iPhone</a>","create_at":"Sat Nov 19 16:55:42 +0000 2022"},{"tweet_id":"1593997466944229377","screen_name":"HyperTzyy","user_name":"HyperTzy","full_text":"@NASA @NASA_SLS @NASA_Orion Woy jangan maen kembang api di bawah roket","sentiment":"neg","source":"<a href=\"http://twitter.com/download/android\" rel=\"nofollow\">Twitter for Android</a>","create_at":"Sat Nov 19 15:59:45 +0000 2022"},{"tweet_id":"1593995231711547393","screen_name":"kgolonel","user_name":"Kendall","full_text":"@tobelieli @NASA jadi malu dipuji","sentiment":"neu","source":"<a href=\"http://twitter.com/download/android\" rel=\"nofollow\">Twitter for Android</a>","create_at":"Sat Nov 19 15:50:52 +0000 2022"},{"tweet_id":"1593994525701070848","screen_name":"tobelieli","user_name":"Biancaᵂᶜᴺ!⋆.ೃ࿔","full_text":"@kgolonel @NASA AAA GABISA CANTIKNYA NATURAL SEKALEEHHH","sentiment":"neu","source":"<a href=\"http://twitter.com/download/iphone\" rel=\"nofollow\">Twitter for iPhone</a>","create_at":"Sat Nov 19 15:48:04 +0000 2022"},{"tweet_id":"1593994393773432832","screen_name":"kgolonel","user_name":"Kendall","full_text":"@tobelieli @NASA halo, yg lebih cantik https://t.co/RS7MDqNKaj","sentiment":"pos","source":"<a href=\"http://twitter.com/download/android\" rel=\"nofollow\">Twitter for Android</a>","create_at":"Sat Nov 19 15:47:33 +0000 2022"},{"tweet_id":"1593994189280186369","screen_name":"tobelieli","user_name":"Biancaᵂᶜᴺ!⋆.ೃ࿔","full_text":"@kgolonel @NASA CANTIK BANGET😍","sentiment":"pos","source":"<a href=\"http://twitter.com/download/iphone\" rel=\"nofollow\">Twitter for iPhone</a>","create_at":"Sat Nov 19 15:46:44 +0000 2022"},{"tweet_id":"1593923997418283010","screen_name":"Mahmut36862060","user_name":"Mahmut","full_text":"@elonmusk @NASA @NASAArtemis @NASA_SLS @NASA_Orion Wooww","sentiment":"neu","source":"<a href=\"http://twitter.com/download/android\" rel=\"nofollow\">Twitter for Android</a>","create_at":"Sat Nov 19 11:07:49 +0000 2022"},{"tweet_id":"1593908459241902081","screen_name":"sandybng7","user_name":"Sandy","full_text":"@tradingbuffet @NASA @Space_Station Hellooooo mam","sentiment":"neu","source":"<a href=\"http://twitter.com/download/android\" rel=\"nofollow\">Twitter for Android</a>","create_at":"Sat Nov 19 10:06:04 +0000 2022"},{"tweet_id":"1593893604639920131","screen_name":"ynjngxings1","user_name":"岩井雄司","full_text":"@NASA @NASAArtemis Raibu kamera kara no gazōdesuga, watashi dakedesu ka?","sentiment":"neu","source":"<a href=\"https://mobile.twitter.com\" rel=\"nofollow\">Twitter Web App</a>","create_at":"Sat Nov 19 09:07:03 +0000 2022"}]
