[{"tweet_id":"1525312535758401537","screen_name":"sleppingforest","user_name":"HERI SETIAWAN","full_text":"$PGAS yang keknya masih akan melanjutkan kenaikan sih. Direkom sejak Selasa, 19 April 2022 silam.\nbisa take profit 10% pada 11 Mei 2022. selo but sure kalau kata pepatah lawas.\nbtw, ini kurang 2 tick aja dari rekom. anggap hit lah ya. wehehe. https://t.co/Ag9rYmHcCR","sentiment":"neg","source":"<a href=\"http://twitter.com/download/iphone\" rel=\"nofollow\">Twitter for iPhone</a>","create_at":"Sat May 14 03:10:22 +0000 2022"},{"tweet_id":"1525308383536066560","screen_name":"sleppingforest","user_name":"HERI SETIAWAN","full_text":"hari kamis kalau ga salah dari rekom oomoo ada yang hit TP. $KKGI dan $PGAS","sentiment":"neg","source":"<a href=\"http://twitter.com/download/iphone\" rel=\"nofollow\">Twitter for iPhone</a>","create_at":"Sat May 14 02:53:52 +0000 2022"}]
