[{"tweet_id":"1527045008678952961","screen_name":"HenryTG6","user_name":"Henry_TG","full_text":"@CryptoIRELAND1 @CornucopiasGame $COPI\n@liqwidfinance $LQ\n@ArdanaProject $DANA\n@Indigo_protocol $INDY (soon)\n@MinswapDEX $MIN","sentiment":"neu","source":"<a href=\"https://mobile.twitter.com\" rel=\"nofollow\">Twitter Web App</a>","create_at":"Wed May 18 21:54:35 +0000 2022"},{"tweet_id":"1526823189203980288","screen_name":"BeritaSahamIdx","user_name":"Berita Saham","full_text":"$HRUM, $PTRO, $INDY, $TOBA, $KKGI\n\nRamai-Ramai Taipan Batu Bara Ekspansi ke Nikel-Mobil Listrik! https://t.co/ILddCW0I4Y","sentiment":"neu","source":"<a href=\"https://mobile.twitter.com\" rel=\"nofollow\">Twitter Web App</a>","create_at":"Wed May 18 07:13:09 +0000 2022"}]
