[{"tweet_id":"1635450132383580161","screen_name":"bebasinvestasi","user_name":"Bebasinvestasi | Bebas - Social Investing App","full_text":"Huaqi (Singapore) Pte Ltd telah menyerap 764 ribu saham baru di PT Kolaka Nickel Indonesia (KNI), anak usaha Vale Indonesia $INCO, sehingga kepemilikan Vale di KNI menjadi 20% dan Huaqi 80%. \n#bebipinter #nickel","sentiment":"pos","source":"<a href=\"https://mobile.twitter.com\" rel=\"nofollow\">Twitter Web App</a>","create_at":"Tue Mar 14 01:17:51 +0000 2023"}]
