[{"tweet_id":"1580167160403415040","screen_name":"rferrajina","user_name":"Mister Rocco","full_text":"BCI  5 T/C routes 180000 18241 -389\nBPI   5 T/C routes 82500 19323 -440\nBSI  10 T/C routes 58328 18788 -68\nBHSI   7 T/C routes 38200 18433 -151\n\nBDI INDEX 1873 -31\n\n#shipping #drybulk #FFA $BDRY\n#capesize #panamax # supermax\n$DSX $EGLE $GBLK $GNK $GOGL $SBLK $SHIP $PANL","sentiment":"neu","source":"<a href=\"https://mobile.twitter.com\" rel=\"nofollow\">Twitter Web App</a>","create_at":"Wed Oct 12 12:03:03 +0000 2022"}]
