[{"tweet_id":"1583354055308574723","screen_name":"SocialMedia_CT","user_name":"Social Media Crypto Tracker","full_text":"Top 1 hour crypto gainers:\n$ARNX %71K+\n$GFNC %492.09+\n$VIA %321.17+\n$PYRK %297.20+\n$BRRR %138.93+\n$RNBW %96.10+\n$MTSP %75.03+\n$MEME %73.54+\n$PEPS %70.09+\n$PIPI %68.14+\n$SYMM %56.85+\n$RBT %52.68+\n$MTRA %48.50+\n$TFC %48.13+\n$EMC %45.91+\n$XTP %45.22+\n$BANANA %44.46+\n$ETHM %40.78+","sentiment":"neu","source":"<a href=\"https://www.socialmediacryptotracker.com\" rel=\"nofollow\">socialmedia_ct_auto_tweeter</a>","create_at":"Fri Oct 21 07:06:38 +0000 2022"}]
