[{"tweet_id":"1548649363383402498","screen_name":"Minhyrung","user_name":"MARK.","full_text":"@bangcasn @good kangen maksimum gue","sentiment":"neu","source":"<a href=\"http://twitter.com/download/android\" rel=\"nofollow\">Twitter for Android</a>","create_at":"Sun Jul 17 12:42:35 +0000 2022"},{"tweet_id":"1548649323269079040","screen_name":"Minhyrung","user_name":"MARK.","full_text":"@Eudwoo @good ohiya! asik banget dong ketemu fans","sentiment":"neu","source":"<a href=\"http://twitter.com/download/android\" rel=\"nofollow\">Twitter for Android</a>","create_at":"Sun Jul 17 12:42:25 +0000 2022"},{"tweet_id":"1548618566286864386","screen_name":"Minhyrung","user_name":"MARK.","full_text":"@KaiaGorber @good hi malam","sentiment":"neu","source":"<a href=\"http://twitter.com/download/android\" rel=\"nofollow\">Twitter for Android</a>","create_at":"Sun Jul 17 10:40:12 +0000 2022"},{"tweet_id":"1548600718407630848","screen_name":"mzyeon","user_name":"Miyeon.","full_text":"@minjeonog @good Cantik BANGEEEET.  Aku hari ini mau bersantai aja sih. Aku juga muak banget sama divink + upchar. :&lt;","sentiment":"pos","source":"<a href=\"http://twitter.com/download/android\" rel=\"nofollow\">Twitter for Android</a>","create_at":"Sun Jul 17 09:29:17 +0000 2022"},{"tweet_id":"1548585651716599808","screen_name":"Chriltopher","user_name":"CHAN.","full_text":"@minjeonog @good Yuk dik kita event yuk","sentiment":"neu","source":"<a href=\"http://twitter.com/download/android\" rel=\"nofollow\">Twitter for Android</a>","create_at":"Sun Jul 17 08:29:25 +0000 2022"},{"tweet_id":"1548584956649099264","screen_name":"minjeonog","user_name":"୨୧","full_text":"@seeunyio @good NYIO KANGEN DEH baru keliatan lagi 🥺","sentiment":"neu","source":"<a href=\"http://twitter.com/download/iphone\" rel=\"nofollow\">Twitter for iPhone</a>","create_at":"Sun Jul 17 08:26:39 +0000 2022"},{"tweet_id":"1548583852016144384","screen_name":"minjeonog","user_name":"୨୧","full_text":"@uanjis @good MALES BANGET NGOBROL SAMA RP TWICE INI","sentiment":"neu","source":"<a href=\"http://twitter.com/download/iphone\" rel=\"nofollow\">Twitter for iPhone</a>","create_at":"Sun Jul 17 08:22:16 +0000 2022"},{"tweet_id":"1548582804341960704","screen_name":"uanjis","user_name":"Proud Saturnine, Hansel. 🐿","full_text":"@minjeonog @good topi mana?","sentiment":"neu","source":"<a href=\"http://twitter.com/download/android\" rel=\"nofollow\">Twitter for Android</a>","create_at":"Sun Jul 17 08:18:06 +0000 2022"},{"tweet_id":"1548546459796004865","screen_name":"JEONGlJ","user_name":"Reputation, Julian.","full_text":"@NMlXXLlLY @good ciaaakh kapan comeback","sentiment":"neu","source":"<a href=\"http://twitter.com/download/android\" rel=\"nofollow\">Twitter for Android</a>","create_at":"Sun Jul 17 05:53:41 +0000 2022"},{"tweet_id":"1548545796622012417","screen_name":"kimchaehyue","user_name":"Mistieden Wizard, Kaluna, JULANGIT. (50/75)","full_text":"@KaiaGorber @good SEMANGAT KAKAK","sentiment":"pos","source":"<a href=\"http://twitter.com/download/android\" rel=\"nofollow\">Twitter for Android</a>","create_at":"Sun Jul 17 05:51:03 +0000 2022"},{"tweet_id":"1548541533594341377","screen_name":"minjeonog","user_name":"୨୧","full_text":"@JUNKYUVI @good boleh kakak bantu aku sekarang? atau kalo boleh bantu upcharnya juga ;)","sentiment":"neu","source":"<a href=\"http://twitter.com/download/iphone\" rel=\"nofollow\">Twitter for iPhone</a>","create_at":"Sun Jul 17 05:34:06 +0000 2022"},{"tweet_id":"1548540194776707075","screen_name":"minjeonog","user_name":"୨୧","full_text":"@uanjis @good disuruh diem terus km udah kaya pu4n, sengaja disensor takut digrebek","sentiment":"neu","source":"<a href=\"http://twitter.com/download/iphone\" rel=\"nofollow\">Twitter for iPhone</a>","create_at":"Sun Jul 17 05:28:47 +0000 2022"},{"tweet_id":"1548540090426617856","screen_name":"minjeonog","user_name":"୨୧","full_text":"@uanjis @good SIAP KK aku udah pake gesper…! 🫡","sentiment":"neg","source":"<a href=\"http://twitter.com/download/iphone\" rel=\"nofollow\">Twitter for iPhone</a>","create_at":"Sun Jul 17 05:28:22 +0000 2022"},{"tweet_id":"1548539675824263169","screen_name":"baeyhi","user_name":"Mistieden, Dispatchers.","full_text":"@NMlXXLlLY @good OMG NAMA KITA SAMA YA KAK ARABELLE, APA KITA SATU PIKIRAN","sentiment":"pos","source":"<a href=\"http://twitter.com/download/android\" rel=\"nofollow\">Twitter for Android</a>","create_at":"Sun Jul 17 05:26:43 +0000 2022"},{"tweet_id":"1548537878732451840","screen_name":"JUNKYUVI","user_name":"Junkyu.","full_text":"@minjeonog @good Aftie Winter. May you also have a good day ahead. Semangat divingnya, sekalian mau bantu diving gak WinterM","sentiment":"pos","source":"<a href=\"http://twitter.com/download/android\" rel=\"nofollow\">Twitter for Android</a>","create_at":"Sun Jul 17 05:19:35 +0000 2022"},{"tweet_id":"1548533993863528448","screen_name":"minjeonog","user_name":"୨୧","full_text":"@good aftie! hari ini kalian mau ngapain aja? kalo aku mau diving sama upchar walaupun tingkat muak diving udah 1000% {senyum_terpaksa}. anyway, have a great day! 🧚🏻‍♂️🌷 https://t.co/4vyhZgWUT2","sentiment":"neg","source":"<a href=\"http://twitter.com/download/iphone\" rel=\"nofollow\">Twitter for iPhone</a>","create_at":"Sun Jul 17 05:04:09 +0000 2022"},{"tweet_id":"1548530351898705920","screen_name":"uanjis","user_name":"Proud Saturnine, Hansel. 🐿","full_text":"@Jinhyrk @good benelan.","sentiment":"neu","source":"<a href=\"http://twitter.com/download/android\" rel=\"nofollow\">Twitter for Android</a>","create_at":"Sun Jul 17 04:49:40 +0000 2022"},{"tweet_id":"1548527011693740033","screen_name":"naurawyu","user_name":"Staff Agent of Joyful, Andreana.","full_text":"@KaiaGorber @good SEMANGAT TAPI JIWAKU LEMES GIMANA YAH KAK T___T","sentiment":"pos","source":"<a href=\"http://twitter.com/download/android\" rel=\"nofollow\">Twitter for Android</a>","create_at":"Sun Jul 17 04:36:24 +0000 2022"},{"tweet_id":"1548525236693241856","screen_name":"joochant","user_name":"jooch.","full_text":"@songkmingi @good udah tidur berapa jam hyung?","sentiment":"neu","source":"<a href=\"http://twitter.com/download/android\" rel=\"nofollow\">Twitter for Android</a>","create_at":"Sun Jul 17 04:29:21 +0000 2022"},{"tweet_id":"1548525072318873600","screen_name":"leesangwron","user_name":"Cleric Rion, BR (HP:23, MP:75)","full_text":"@KaiaGorber @good Aku dah siap berantem","sentiment":"neg","source":"<a href=\"http://twitter.com/download/android\" rel=\"nofollow\">Twitter for Android</a>","create_at":"Sun Jul 17 04:28:42 +0000 2022"},{"tweet_id":"1548523604371197953","screen_name":"FJlSU","user_name":"Ailyn.","full_text":"@NMlXXLlLY @good kok hobinya cuma membantu ibu? kenapa gak bantu bapak juga?","sentiment":"pos","source":"<a href=\"http://twitter.com/download/android\" rel=\"nofollow\">Twitter for Android</a>","create_at":"Sun Jul 17 04:22:52 +0000 2022"},{"tweet_id":"1548523458417819655","screen_name":"kagrina","user_name":"Rogue El, EVOS (HP:60, MP:40)","full_text":"@astahi @good Wdyt sama OrGil yang ngaku ngaku jadi Naevis? MYs serang dia.","sentiment":"neu","source":"<a href=\"http://twitter.com/download/android\" rel=\"nofollow\">Twitter for Android</a>","create_at":"Sun Jul 17 04:22:17 +0000 2022"},{"tweet_id":"1548523020276596736","screen_name":"SKITXHMIX","user_name":"hale on duuuuuty","full_text":"@NMlXXLlLY @good LUCU BANGET DAH CIAA sodaranya cie ya","sentiment":"pos","source":"<a href=\"http://twitter.com/download/android\" rel=\"nofollow\">Twitter for Android</a>","create_at":"Sun Jul 17 04:20:32 +0000 2022"},{"tweet_id":"1548521965417541632","screen_name":"Yujgin","user_name":"Rogue, Deline EVOS. (HP: 60, MP: 70)","full_text":"@KaiaGorber @good AAAA LEMES BELUM DIUCAPIN MORNING SAMA KAMU","sentiment":"neu","source":"<a href=\"http://twitter.com/download/android\" rel=\"nofollow\">Twitter for Android</a>","create_at":"Sun Jul 17 04:16:21 +0000 2022"},{"tweet_id":"1548520165129605120","screen_name":"Jaehyune","user_name":"Listeners, Gerfin","full_text":"@KaiaGorber @good Masih ngantuk 😴","sentiment":"neg","source":"<a href=\"http://twitter.com/download/iphone\" rel=\"nofollow\">Twitter for iPhone</a>","create_at":"Sun Jul 17 04:09:12 +0000 2022"},{"tweet_id":"1548517443026714624","screen_name":"Mincu","user_name":"Heroes, Staff, Enma. ຳ☁︎","full_text":"@KaiaGorber @good KANGEEEEEEEN. SEMANGAT DONG. 🥺😍","sentiment":"pos","source":"<a href=\"http://twitter.com/download/iphone\" rel=\"nofollow\">Twitter for iPhone</a>","create_at":"Sun Jul 17 03:58:23 +0000 2022"},{"tweet_id":"1548516891890958338","screen_name":"Yejgii","user_name":"YJ.","full_text":"@KaiaGorber @good gumoning aku lemes *pingsan*","sentiment":"neu","source":"<a href=\"http://twitter.com/download/android\" rel=\"nofollow\">Twitter for Android</a>","create_at":"Sun Jul 17 03:56:11 +0000 2022"},{"tweet_id":"1548516082192773120","screen_name":"wnonyu","user_name":"wonyo","full_text":"@bangcasn @good betul! rebahan 25/8","sentiment":"neu","source":"<a href=\"http://twitter.com/download/android\" rel=\"nofollow\">Twitter for Android</a>","create_at":"Sun Jul 17 03:52:58 +0000 2022"},{"tweet_id":"1548515930321276928","screen_name":"TAEHYUUIN","user_name":"Paladin of SHADYSIDE Kala, Evos (140/20)","full_text":"@KaiaGorber @good Siap loyo, Paladin Tessy.","sentiment":"neg","source":"<a href=\"http://twitter.com/download/android\" rel=\"nofollow\">Twitter for Android</a>","create_at":"Sun Jul 17 03:52:22 +0000 2022"},{"tweet_id":"1548515407882899456","screen_name":"KaiaGorber","user_name":"Staff, Paladin Tessy, Jandaz (HP: 140, MP: 30)","full_text":"@enhypenyang @good JANDAZ YANG SATU INI SEMANGAT YAAK 💜 BORAHAE 💜","sentiment":"pos","source":"<a href=\"http://twitter.com/download/iphone\" rel=\"nofollow\">Twitter for iPhone</a>","create_at":"Sun Jul 17 03:50:17 +0000 2022"},{"tweet_id":"1548514477280473088","screen_name":"LEEKN0WD","user_name":"Danta","full_text":"@NMlXXLlLY @good Cia kamu ke rumahku aja kebetulan butuh bantuan kan kata.a suka bantu https://t.co/kd1Qw3e7Do","sentiment":"neg","source":"<a href=\"http://twitter.com/download/android\" rel=\"nofollow\">Twitter for Android</a>","create_at":"Sun Jul 17 03:46:36 +0000 2022"},{"tweet_id":"1548514423723413507","screen_name":"blackpinkninni","user_name":"Staff, Nala.","full_text":"@KaiaGorber @good Aku gak ikut eventnya..😔","sentiment":"neu","source":"<a href=\"http://twitter.com/download/iphone\" rel=\"nofollow\">Twitter for iPhone</a>","create_at":"Sun Jul 17 03:46:23 +0000 2022"},{"tweet_id":"1548512718398885888","screen_name":"Unoffisial","user_name":"Fighter Pur, JULANGIT. 140/20","full_text":"@KaiaGorber @good Semangat Paladin Tessy 🤣🚓","sentiment":"pos","source":"<a href=\"http://twitter.com/download/android\" rel=\"nofollow\">Twitter for Android</a>","create_at":"Sun Jul 17 03:39:36 +0000 2022"},{"tweet_id":"1548511850081316864","screen_name":"KaiaGorber","user_name":"Staff, Paladin Tessy, Jandaz (HP: 140, MP: 30)","full_text":"@good morning semuanyah, udah semangat buat event hari ini? 🧏‍♂️","sentiment":"pos","source":"<a href=\"http://twitter.com/download/iphone\" rel=\"nofollow\">Twitter for iPhone</a>","create_at":"Sun Jul 17 03:36:09 +0000 2022"},{"tweet_id":"1548504219199864839","screen_name":"Jinhyrk","user_name":"JH.","full_text":"@uanjis @good Nyang bener,,,,","sentiment":"neu","source":"<a href=\"http://twitter.com/download/android\" rel=\"nofollow\">Twitter for Android</a>","create_at":"Sun Jul 17 03:05:50 +0000 2022"},{"tweet_id":"1548503625269317638","screen_name":"cahewoun","user_name":"Mistieden Staff, Thea.","full_text":"@songkmingi @good GAK DULU. aku lelah..","sentiment":"neg","source":"<a href=\"http://twitter.com/download/android\" rel=\"nofollow\">Twitter for Android</a>","create_at":"Sun Jul 17 03:03:28 +0000 2022"}]
