[{"tweet_id":"1563336360114933760","screen_name":"Sarah1003sa","user_name":"Crypto Token Alerts","full_text":"Become the best trader with us: https://t.co/q2E4WFe4U1\n\n$AMD $SNDL $MOBL $PLUG $GNUS $QQQ $UONE $PTON $ACOR $NAKD $WWR $SRNE $NKLA $TQQQ $WKHS $PLL $DKNG $ZOM $SUNW $SOLO $SNDL $PRTY $POLA $ONTX $OEG $OAS $NNDM $NCTY $JE $IDEX $GNUS https://t.co/O7dzd4CJTz","sentiment":"neu","source":"<a href=\"http://twitter.com/download/android\" rel=\"nofollow\">Twitter for Android</a>","create_at":"Sat Aug 27 01:23:28 +0000 2022"}]
