[{"tweet_id":"1610674988331446273","screen_name":"Ruudriick616","user_name":"RuudriickReborn","full_text":"@TiffaJessi @JuJulienDev @chhopsky @FaidesTwitch @Respawn @PlayApex Solo Qeueing is stressful 😂","sentiment":"pos","source":"<a href=\"http://twitter.com/download/android\" rel=\"nofollow\">Twitter for Android</a>","create_at":"Wed Jan 04 16:30:16 +0000 2023"},{"tweet_id":"1610643733539876864","screen_name":"wahyuvicko","user_name":"w","full_text":"$APEX jangan ARA dulu dong, pliss...\n\nSideway aja yg lama satu tahun gapapa / turun lagi juga bole bgt, blm puas akum aku\n\nAyolah di fear lagi APEX nya donk sampai Q1 keluar. Selama target 27K lot blm tercapai jgn rally dulu $BOSS\n\n$PTBA $ITMG $SMMT $BSSR $BUMI #HODL #coal https://t.co/n222it9Z3C","sentiment":"pos","source":"<a href=\"https://mobile.twitter.com\" rel=\"nofollow\">Twitter Web App</a>","create_at":"Wed Jan 04 14:26:05 +0000 2023"},{"tweet_id":"1610600311500214272","screen_name":"ayon_kra","user_name":"YeeYee","full_text":"@Dropped @PlayApex @kinshuk1k bc ye dekh","sentiment":"neu","source":"<a href=\"http://twitter.com/download/android\" rel=\"nofollow\">Twitter for Android</a>","create_at":"Wed Jan 04 11:33:32 +0000 2023"},{"tweet_id":"1610449334750904320","screen_name":"ItzTheDub4","user_name":"ItzTheDub","full_text":"@BashhVIII @PlayApex Mesmerizing","sentiment":"neu","source":"<a href=\"http://twitter.com/download/iphone\" rel=\"nofollow\">Twitter for iPhone</a>","create_at":"Wed Jan 04 01:33:36 +0000 2023"},{"tweet_id":"1610381632346935296","screen_name":"C2MK_Sec","user_name":"Sec","full_text":"Ayoo? @PlayApex 🧐\nhttps://t.co/tuVd0oynxJ","sentiment":"neu","source":"<a href=\"https://mobile.twitter.com\" rel=\"nofollow\">Twitter Web App</a>","create_at":"Tue Jan 03 21:04:35 +0000 2023"},{"tweet_id":"1610341891354025985","screen_name":"HolyPablo_","user_name":"TheHolyPablo","full_text":"@drumbum_ @PlayApex YESSSRRRRR","sentiment":"neu","source":"<a href=\"http://twitter.com/download/iphone\" rel=\"nofollow\">Twitter for iPhone</a>","create_at":"Tue Jan 03 18:26:40 +0000 2023"},{"tweet_id":"1610314960034299906","screen_name":"iiTzCherri","user_name":"cherri🍒🌸","full_text":"free kp 🤭 \n@PlayApex https://t.co/jHOcrXbQnl","sentiment":"neu","source":"<a href=\"http://twitter.com/download/iphone\" rel=\"nofollow\">Twitter for iPhone</a>","create_at":"Tue Jan 03 16:39:39 +0000 2023"}]
