[{"tweet_id":"1537607547053428736","screen_name":"indopremier","user_name":"Indo Premier Sekuritas","full_text":"$ICBP\n\nHarga ditutup di atas EMA5,10 dan membentuk pola doji yang merupakan sinyal indecision, stochastic netral dan MACD histogram divergence negatif.\n\nCurrent Price : 8.675\nTarget Harga 1 : 8.750\nTarget Harga 2 : 8.825\nCut Loss : &lt; 8.525","sentiment":"neg","source":"<a href=\"https://mobile.twitter.com\" rel=\"nofollow\">Twitter Web App</a>","create_at":"Fri Jun 17 01:26:21 +0000 2022"},{"tweet_id":"1537607467177086977","screen_name":"indopremier","user_name":"Indo Premier Sekuritas","full_text":"$ICBP\nRekomendasi : Buy\nTime Horizon 1 - 5 hari\n\nICBP membukukan laba bersih pada Q122 sebesar Rp1,94 triliun. Naik bila dibanding periode yang sama tahun 2021 sebesar Rp1,74 triliun. Dengan demikian, laba bersih per saham setara dengan Rp165,9/lembar.","sentiment":"pos","source":"<a href=\"https://mobile.twitter.com\" rel=\"nofollow\">Twitter Web App</a>","create_at":"Fri Jun 17 01:26:02 +0000 2022"}]
