[{"tweet_id":"1570530228338040833","screen_name":"WengerVision","user_name":"Abid","full_text":"@Mclovin57437362 @AlasdairGold Kulu coming to Arsenal","sentiment":"neu","source":"<a href=\"http://twitter.com/download/iphone\" rel=\"nofollow\">Twitter for iPhone</a>","create_at":"Thu Sep 15 21:49:20 +0000 2022"},{"tweet_id":"1570430659214315520","screen_name":"lander_11s","user_name":"Lander","full_text":"#XAUUSD $XAUUSD #Gold $Gold\nLong term context: https://t.co/JDtkhMN6rG","sentiment":"neu","source":"<a href=\"https://mobile.twitter.com\" rel=\"nofollow\">Twitter Web App</a>","create_at":"Thu Sep 15 15:13:41 +0000 2022"},{"tweet_id":"1570424867346059264","screen_name":"TheFootyCafe","user_name":"TheFootyCafe","full_text":"@AlasdairGold Go on conte go perisic rwb &amp; sess LWB on sat…","sentiment":"neu","source":"<a href=\"https://mobile.twitter.com\" rel=\"nofollow\">Twitter Web App</a>","create_at":"Thu Sep 15 14:50:40 +0000 2022"},{"tweet_id":"1570418103900667909","screen_name":"itskamran7","user_name":"Kamran","full_text":"@AlasdairGold 3Bissouma","sentiment":"neu","source":"<a href=\"http://twitter.com/download/iphone\" rel=\"nofollow\">Twitter for iPhone</a>","create_at":"Thu Sep 15 14:23:47 +0000 2022"},{"tweet_id":"1570376890749427713","screen_name":"jayi_wang","user_name":"James Jayi Wang","full_text":"22-37-3/ $Gold #Gold\n$XAU $XAUUSD #XAUUSD\nWED SEP 14, 2022\nC: $1,697.60 (-4.71/-0.28%)\n52wk range :\n1,678.40~2,078.80\n52wks : -3.12%\nYTD : -7.18%\nhttps://t.co/O2ID09DbVc\nhttps://t.co/Sc3h4Nr3o1\nhttps://t.co/PrOYt91Kvx https://t.co/7JzkH9Vpzc","sentiment":"neu","source":"<a href=\"http://twitter.com/download/android\" rel=\"nofollow\">Twitter for Android</a>","create_at":"Thu Sep 15 11:40:01 +0000 2022"},{"tweet_id":"1570370652225392641","screen_name":"itsmtuk","user_name":"MTUK","full_text":"TP hit ✅ \n\n#XAUUSD #GOLD $XAUUSD $GOLD #USD $USD https://t.co/fIzTnPJuVT","sentiment":"pos","source":"<a href=\"http://twitter.com/#!/download/ipad\" rel=\"nofollow\">Twitter for iPad</a>","create_at":"Thu Sep 15 11:15:14 +0000 2022"},{"tweet_id":"1570370617593024515","screen_name":"itsmtuk","user_name":"MTUK","full_text":"TP hit ✅ \n\n#XAUUSD #GOLD $XAUUSD $GOLD #USD $USD https://t.co/uLmOMnryXn","sentiment":"pos","source":"<a href=\"http://twitter.com/#!/download/ipad\" rel=\"nofollow\">Twitter for iPad</a>","create_at":"Thu Sep 15 11:15:05 +0000 2022"},{"tweet_id":"1570366253763817472","screen_name":"wavetradr","user_name":"WAVETRADER","full_text":"Sold #wavetrader EURUSD 0.99791 #forex #scalper #autopilot #gold $gold #gbpjpy $gbpjpy #us30 $us30 #eurusd $eurusd #gbpusd $gbpusd","sentiment":"neu","source":"<a href=\"https://www.myfxbook.com\" rel=\"nofollow\">Myfxbook</a>","create_at":"Thu Sep 15 10:57:45 +0000 2022"},{"tweet_id":"1570293467187761153","screen_name":"RenownedTrader","user_name":"J","full_text":"TP hit ✅ \n\n#XAUUSD #GOLD $XAUUSD $GOLD #USD $USD https://t.co/uYuFI6opEV","sentiment":"pos","source":"<a href=\"http://twitter.com/#!/download/ipad\" rel=\"nofollow\">Twitter for iPad</a>","create_at":"Thu Sep 15 06:08:31 +0000 2022"},{"tweet_id":"1570293388381159426","screen_name":"RenownedTrader","user_name":"J","full_text":"TP hit ✅ \n\n#XAUUSD #GOLD $XAUUSD $GOLD #USD $USD https://t.co/Jl4mtJHPBm","sentiment":"pos","source":"<a href=\"http://twitter.com/#!/download/ipad\" rel=\"nofollow\">Twitter for iPad</a>","create_at":"Thu Sep 15 06:08:13 +0000 2022"},{"tweet_id":"1570292742336684038","screen_name":"itsmtuk","user_name":"MTUK","full_text":"TP hit ✅ \n\n#XAUUSD #GOLD $XAUUSD $GOLD #USD $USD https://t.co/SFLXxwgMcy","sentiment":"pos","source":"<a href=\"http://twitter.com/#!/download/ipad\" rel=\"nofollow\">Twitter for iPad</a>","create_at":"Thu Sep 15 06:05:39 +0000 2022"},{"tweet_id":"1570292706944884736","screen_name":"itsmtuk","user_name":"MTUK","full_text":"TP hit ✅ \n\n#XAUUSD #GOLD $XAUUSD $GOLD #USD $USD https://t.co/iOElWEfnk5","sentiment":"pos","source":"<a href=\"http://twitter.com/#!/download/ipad\" rel=\"nofollow\">Twitter for iPad</a>","create_at":"Thu Sep 15 06:05:30 +0000 2022"},{"tweet_id":"1570261601684692993","screen_name":"Gregory_Ozimec","user_name":"Gregory Ozimec","full_text":"@QTRResearch $jepi $gold","sentiment":"neu","source":"<a href=\"https://mobile.twitter.com\" rel=\"nofollow\">Twitter Web App</a>","create_at":"Thu Sep 15 04:01:54 +0000 2022"},{"tweet_id":"1570261371178352640","screen_name":"wavetradr","user_name":"WAVETRADER","full_text":"Sold #wavetrader EURUSD 0.99729 #forex #scalper #autopilot #gold $gold #gbpjpy $gbpjpy #us30 $us30 #eurusd $eurusd #gbpusd $gbpusd","sentiment":"neu","source":"<a href=\"https://www.myfxbook.com\" rel=\"nofollow\">Myfxbook</a>","create_at":"Thu Sep 15 04:00:59 +0000 2022"},{"tweet_id":"1570230524047917058","screen_name":"wavetradr","user_name":"WAVETRADER","full_text":"Sold #wavetrader EURUSD 0.99762 #forex #scalper #autopilot #gold $gold #gbpjpy $gbpjpy #us30 $us30 #eurusd $eurusd #gbpusd $gbpusd","sentiment":"neu","source":"<a href=\"https://www.myfxbook.com\" rel=\"nofollow\">Myfxbook</a>","create_at":"Thu Sep 15 01:58:25 +0000 2022"}]
