[{"tweet_id":"1605289572778512386","screen_name":"LeBronJ19571083","user_name":"LeBron James 📈","full_text":"TOP 10 #TVL ON BINANCE SMART CHAI\nhttps://t.co/VM0N8POW4w\n\n$BTC $ETH $XRP $BNB $DOGE $LTC $SOL $MATIC $ADA $LINK $LUNC $DOT $ALGO $SHIB $USDC $USDT\n$LSK $MTL $RAD $MAGIC $SCRT $ACH $GMX $UMA $YFII $NEBL https://t.co/WUBXxBpfib","sentiment":"neu","source":"<a href=\"http://twitter.com/download/android\" rel=\"nofollow\">Twitter for Android</a>","create_at":"Tue Dec 20 19:50:33 +0000 2022"},{"tweet_id":"1605287849204805633","screen_name":"LeBronJ19571083","user_name":"LeBron James 📈","full_text":"TOP 10 #TVL ON BINANCE SMART CHAI\nhttps://t.co/VM0N8POW4w\n\n$BTC $ETH $XRP $BNB $DOGE $LTC $SOL $MATIC $ADA $LINK $LUNC $DOT $ALGO $SHIB $USDC $USDT\n$LSK $MTL $RAD $MAGIC $SCRT $ACH $GMX $UMA $YFII $NEBL https://t.co/G6xovUHcPO","sentiment":"neu","source":"<a href=\"http://twitter.com/download/android\" rel=\"nofollow\">Twitter for Android</a>","create_at":"Tue Dec 20 19:43:42 +0000 2022"},{"tweet_id":"1605282676331540480","screen_name":"lasn0997","user_name":"lasn0997","full_text":"$BTC $ETH $LINK $XTZ $ADA $VET $KNC $SXP $TWTR $ES $JD $BABA $BIDU $TME \n$SPY $QQQ $DIS $TSLA $SHOP\n\nhttps://t.co/4AkwemBHfK https://t.co/RR7fd00Ysv","sentiment":"neu","source":"<a href=\"http://twitter.com/download/android\" rel=\"nofollow\">Twitter for Android</a>","create_at":"Tue Dec 20 19:23:09 +0000 2022"},{"tweet_id":"1605270154325417984","screen_name":"janis_klocko","user_name":"Janis Klocko","full_text":"Best Best Best :O\nhttps://t.co/qJ62BxCail\n\n$BTC $ETH $XRP $BNB $DOGE $LTC $SOL $MATIC $ADA $LINK $SNM $BEAM $MAGIC $BNX $POLYX $CTXC $YFII $CTXC $REQ $PSG $hot https://t.co/UehIsyalHQ","sentiment":"neu","source":"<a href=\"https://mobile.twitter.com\" rel=\"nofollow\">Twitter Web App</a>","create_at":"Tue Dec 20 18:33:23 +0000 2022"},{"tweet_id":"1605268875591188480","screen_name":"Nisha97232379","user_name":"Nisha","full_text":"$ETH  TOP analysis price target for next week..🙏https://t.co/l1kYYpHfK1\n\n$BTC $ETH $XRP $BNB $DOGE $LTC $SOL $MATIC $ADA $LINK $SNM $BEAM $MAGIC $BNX $POLYX $CTXC $YFII $CTXC $REQ $PSG $eth https://t.co/MAgYodD7i0","sentiment":"neu","source":"<a href=\"https://mobile.twitter.com\" rel=\"nofollow\">Twitter Web App</a>","create_at":"Tue Dec 20 18:28:19 +0000 2022"},{"tweet_id":"1605268554672398336","screen_name":"SusanSouth13","user_name":"Susan South","full_text":"TOP MOST VISITED COINS BY PRICE PERFORMANCE \nhttps://t.co/TKFgtEOJzZ\n\n$BTC $ETH $XRP $BNB $DOGE $LTC $SOL $MATIC $ADA $LINK $SNM $BEAM $MAGIC $BNX $POLYX $CTXC $YFII $CTXC $REQ $PSG $lazio https://t.co/lzh5oAuKO4","sentiment":"neu","source":"<a href=\"https://mobile.twitter.com\" rel=\"nofollow\">Twitter Web App</a>","create_at":"Tue Dec 20 18:27:02 +0000 2022"},{"tweet_id":"1605268066291417088","screen_name":"janis_klocko","user_name":"Janis Klocko","full_text":"$WOO #Bitcoin    in it's highest peak right now... https://t.co/qJ62BxTdkl\n\n$BTC $ETH $XRP $BNB $DOGE $LTC $SOL $MATIC $ADA $LINK $SNM $BEAM $MAGIC $BNX $POLYX $CTXC $YFII $CTXC $REQ $PSG $ELF https://t.co/Fux4KOLmAH","sentiment":"neu","source":"<a href=\"https://mobile.twitter.com\" rel=\"nofollow\">Twitter Web App</a>","create_at":"Tue Dec 20 18:25:06 +0000 2022"},{"tweet_id":"1605267573968601088","screen_name":"Nisha97232379","user_name":"Nisha","full_text":"⚡️TOP GAINERS OF THE DAY! \n31 October 2022 ➡\nhttps://t.co/l1kYYpHfK1\n\n$BTC $ETH $XRP $BNB $DOGE $LTC $SOL $MATIC $ADA $LINK $SNM $BEAM $MAGIC $BNX $POLYX $CTXC $YFII $CTXC $REQ $PSG $snx https://t.co/nyNBenTg0c","sentiment":"neu","source":"<a href=\"https://mobile.twitter.com\" rel=\"nofollow\">Twitter Web App</a>","create_at":"Tue Dec 20 18:23:08 +0000 2022"},{"tweet_id":"1605261895526928386","screen_name":"CRYPTO78926394","user_name":"CRYPTO","full_text":"Swing 🚥\n\n$HNT 🟡 $33.75\n$CELO 🟢 $4.06\n$OMG 🟡 $5.91\n$DASH 🟡 $127.20\n$gala $ETH\nhttps://t.co/OKeR86sug2\n\n$BTC $ETH $DOGE $SOL $XRP $BNB  $LTC  $MATIC $ADA $LINK $LUNC $DOT $ALGO $SHIB $USDC $USDT $SNM $BEAM $MAGIC $BNX $POLYX $CTXC $YFII https://t.co/oDGpl6iYSc","sentiment":"neu","source":"<a href=\"http://twitter.com/download/android\" rel=\"nofollow\">Twitter for Android</a>","create_at":"Tue Dec 20 18:00:34 +0000 2022"},{"tweet_id":"1605258145261301760","screen_name":"Crypton04415782","user_name":"Crypto news","full_text":"⚡️TOP GAINERS OF THE DAY! \n31 October 2022 ➡ \nhttps://t.co/3BJHQSaFKL\n\n$BTC $ETH $XRP $BNB $DOGE $LTC $SOL $MATIC $ADA $LINK $SNM $BEAM $MAGIC $BNX $POLYX $CTXC $YFII $CTXC $REQ $PSG $atom https://t.co/LwgN0I8y7v","sentiment":"neu","source":"<a href=\"https://mobile.twitter.com\" rel=\"nofollow\">Twitter Web App</a>","create_at":"Tue Dec 20 17:45:40 +0000 2022"},{"tweet_id":"1605257562793791488","screen_name":"Melanie43031650","user_name":"Melanie","full_text":"I don't remember ever being this\n\n happy...\nhttps://t.co/eNNzpY6ljO\n\n$BTC $ETH $XRP $BNB $DOGE $LTC $SOL $MATIC $ADA $LINK $SNM $BEAM $MAGIC $BNX $POLYX $CTXC $YFII $CTXC $REQ $PSG $ckb https://t.co/cL6sbYprwP","sentiment":"neu","source":"<a href=\"https://mobile.twitter.com\" rel=\"nofollow\">Twitter Web App</a>","create_at":"Tue Dec 20 17:43:21 +0000 2022"},{"tweet_id":"1605257266084859904","screen_name":"Nisha97232379","user_name":"Nisha","full_text":"⚡️​​Trending Searches by\n\n CoinGecko...\nhttps://t.co/l1kYYpHfK1\n\n$BTC $ETH $XRP $BNB $DOGE $LTC $SOL $MATIC $ADA $LINK $SNM $BEAM $MAGIC $BNX $POLYX $CTXC $YFII $CTXC $REQ $PSG $twt https://t.co/m2f3cvRSJn","sentiment":"neu","source":"<a href=\"https://mobile.twitter.com\" rel=\"nofollow\">Twitter Web App</a>","create_at":"Tue Dec 20 17:42:11 +0000 2022"},{"tweet_id":"1605257132970225664","screen_name":"chat2_trading","user_name":"Trading Chat","full_text":"Swing 🚥\n\n$HNT 🟡 $33.75\n$CELO 🟢 $4.06\n$OMG 🟡 $5.91\n$DASH 🟡 $127.20\n$gala $ETH\nhttps://t.co/7Lypd4mFZk\n\n$BTC $ETH $DOGE $SOL $XRP $BNB  $LTC  $MATIC $ADA $LINK $LUNC $DOT $ALGO $SHIB $USDC $USDT $SNM $BEAM $MAGIC $BNX $POLYX $CTXC $YFII https://t.co/iCb8fvyYku","sentiment":"neu","source":"<a href=\"http://twitter.com/download/android\" rel=\"nofollow\">Twitter for Android</a>","create_at":"Tue Dec 20 17:41:39 +0000 2022"},{"tweet_id":"1605254023908565001","screen_name":"ActsOfK1ndness","user_name":"xCrypto","full_text":"$XHV  great project!  DYOR\n@HavenXHV\n\n$BTC $ETH $matic $LTC $DOGE $XRP $ADA $TRX  $DOT $vet $icx $LINK #defi $ZIL  $ALPHA $TOMO $DLT $TWT $ATOM $gme #defi $arrr $SHA $LUNA $MANA $xmv $clv $RSR $cc $shib $KAI $sol $woo $dash $meta $mri $tsla $mana $cb $shib $iota $amc $gme $tesla","sentiment":"neu","source":"<a href=\"http://twitter.com/download/android\" rel=\"nofollow\">Twitter for Android</a>","create_at":"Tue Dec 20 17:29:18 +0000 2022"},{"tweet_id":"1605237198408028160","screen_name":"LeBronJ19571083","user_name":"LeBron James 📈","full_text":"Swing 🚥\n\n$HNT 🟡 $33.75\n$CELO 🟢 $4.06\n$OMG 🟡 $5.91\n$DASH 🟡 $127.20\n$gala $ETH\nhttps://t.co/VM0N8POW4w\n\n$BTC $ETH $DOGE $SOL $XRP $BNB  $LTC  $MATIC $ADA $LINK $LUNC $DOT $ALGO $SHIB $USDC $USDT $SNM $BEAM $MAGIC $BNX $POLYX $CTXC $YFII https://t.co/wAvk5VXgGA","sentiment":"neu","source":"<a href=\"http://twitter.com/download/android\" rel=\"nofollow\">Twitter for Android</a>","create_at":"Tue Dec 20 16:22:26 +0000 2022"},{"tweet_id":"1605235706930286592","screen_name":"KingsMa06664790","user_name":"King","full_text":"Swing 🚥\n\n$HNT 🟡 $33.75\n$CELO 🟢 $4.06\n$OMG 🟡 $5.91\n$DASH 🟡 $127.20\n$gala $ETH\nhttps://t.co/gtjV0hzdds\n\n$BTC $ETH $DOGE $SOL $XRP $BNB  $LTC  $MATIC $ADA $LINK $LUNC $DOT $ALGO $SHIB $USDC $USDT $SNM $BEAM $MAGIC $BNX $POLYX $CTXC $YFII https://t.co/cmYOPXlMMD","sentiment":"neu","source":"<a href=\"http://twitter.com/download/android\" rel=\"nofollow\">Twitter for Android</a>","create_at":"Tue Dec 20 16:16:31 +0000 2022"},{"tweet_id":"1605229338945015809","screen_name":"Dominic42422840","user_name":"Dominic Murphy📈","full_text":"TOP 10 #TVL ON BINANCE SMART CHAI\nhttps://t.co/izlO7iGeSE\n\n$BTC $ETH $DOGE $SOL $XRP $BNB  $LTC  $MATIC $ADA $LINK $LUNC $DOT $ALGO $SHIB $USDC $USDT $SNM $BEAM $MAGIC $BNX $POLYX $CTXC $YFII https://t.co/3fKiiLV3oV","sentiment":"neu","source":"<a href=\"http://twitter.com/download/android\" rel=\"nofollow\">Twitter for Android</a>","create_at":"Tue Dec 20 15:51:12 +0000 2022"},{"tweet_id":"1605213172298051585","screen_name":"LeBronJ19571083","user_name":"LeBron James 📈","full_text":"Profitable Crypto Trading Group\n➡https://t.co/VM0N8POW4w\n\n$BTC $ETH $DOGE $SOL $XRP $BNB  $LTC  $MATIC $ADA $LINK $LUNC $DOT $ALGO $SHIB $USDC $USDT $SNM $BEAM $MAGIC $BNX $POLYX $CTXC $YFII https://t.co/pAB085ECyP","sentiment":"neu","source":"<a href=\"http://twitter.com/download/android\" rel=\"nofollow\">Twitter for Android</a>","create_at":"Tue Dec 20 14:46:58 +0000 2022"},{"tweet_id":"1605211674998628352","screen_name":"LeBronJ19571083","user_name":"LeBron James 📈","full_text":"Swing 🚥\n\n$HNT 🟡 $33.75\n$CELO 🟢 $4.06\n$OMG 🟡 $5.91\n$DASH 🟡 $127.20\n$gala $ETH\nhttps://t.co/VM0N8POW4w\n\n$BTC $ETH $DOGE $SOL $XRP $BNB  $LTC  $MATIC $ADA $LINK $LUNC $DOT $ALGO $SHIB $USDC $USDT $SNM $BEAM $MAGIC $BNX $POLYX $CTXC $YFII https://t.co/Nqqe64uw8t","sentiment":"neu","source":"<a href=\"http://twitter.com/download/android\" rel=\"nofollow\">Twitter for Android</a>","create_at":"Tue Dec 20 14:41:01 +0000 2022"},{"tweet_id":"1605208359136858114","screen_name":"kimani97855968","user_name":"ki70","full_text":"$btc $eth $usdt $usdc $bnb $xrp $ada $doge $matic $shib $dot $dai $trx $ltc $twt $sol $uni $avac $link\n#btc #eth #ftx #crypto #noncustodial #wallet #binance #bnb https://t.co/mfF91Ettfg","sentiment":"neu","source":"<a href=\"https://mobile.twitter.com\" rel=\"nofollow\">Twitter Web App</a>","create_at":"Tue Dec 20 14:27:50 +0000 2022"},{"tweet_id":"1605205423245885440","screen_name":"MoonBirds15","user_name":"MoonBirds 📊","full_text":"Profitable Crypto Trading Group\n➡https://t.co/CuKj1XsHDT\n\n$BTC $ETH $DOGE $SOL $XRP $BNB  $LTC  $MATIC $ADA $LINK $LUNC $DOT $ALGO $SHIB $USDC $USDT $SNM $BEAM $MAGIC $BNX $POLYX $CTXC $YFII https://t.co/luq1xDKcc5","sentiment":"neu","source":"<a href=\"http://twitter.com/download/android\" rel=\"nofollow\">Twitter for Android</a>","create_at":"Tue Dec 20 14:16:10 +0000 2022"},{"tweet_id":"1605187156900982784","screen_name":"CorserLola","user_name":"Lola Corser","full_text":"Profitable Crypto Trading Group\n\nhttps://t.co/mrcIFRZqFf\n\n$BTC $ETH $DOGE $SOL $XRP $BNB  $LTC  $MATIC $ADA $LINK $LUNC $DOT $ALGO $SHIB $USDC $USDT $SNM $BEAM $MAGIC $BNX $POLYX $CTXC $YFII https://t.co/OfaFemSnXO","sentiment":"neu","source":"<a href=\"https://mobile.twitter.com\" rel=\"nofollow\">Twitter Web App</a>","create_at":"Tue Dec 20 13:03:35 +0000 2022"},{"tweet_id":"1605175632098648065","screen_name":"seeashon","user_name":"seeashon","full_text":"TOP 10 TVL ON SOLANA\nhttps://t.co/SP5dEA8EUP\n\n$SBR $SUNNY $RAY $SRM $ORCA $MNDE $TULIP #ATRIX $PAI $ALM $LINK https://t.co/Zk4qSvZd18","sentiment":"neu","source":"<a href=\"http://twitter.com/download/android\" rel=\"nofollow\">Twitter for Android</a>","create_at":"Tue Dec 20 12:17:48 +0000 2022"},{"tweet_id":"1605163451005161473","screen_name":"Miketys93226732","user_name":"Mike tyson 📈","full_text":"TOP 10 #TVL ON BINANCE SMART CHAI\nhttps://t.co/n1dj0dIWrk\n\n$BTC $ETH $DOGE $SOL $XRP $BNB  $LTC  $MATIC $ADA $LINK $LUNC $DOT $ALGO $SHIB $USDC $USDT $SNM $BEAM $MAGIC $BNX $POLYX $CTXC $YFII https://t.co/BBscXjOKT3","sentiment":"neu","source":"<a href=\"http://twitter.com/download/android\" rel=\"nofollow\">Twitter for Android</a>","create_at":"Tue Dec 20 11:29:23 +0000 2022"},{"tweet_id":"1605155902633676808","screen_name":"KingsMa06664790","user_name":"King","full_text":"Swing 🚥\n\n$HNT 🟡 $33.75\n$CELO 🟢 $4.06\n$OMG 🟡 $5.91\n$DASH 🟡 $127.20\n$gala $ETH\nhttps://t.co/gtjV0hzdds\n\n$BTC $ETH $DOGE $SOL $XRP $BNB  $LTC  $MATIC $ADA $LINK $LUNC $DOT $ALGO $SHIB $USDC $USDT $SNM $BEAM $MAGIC $BNX $POLYX $CTXC $YFIl https://t.co/B6DM7AdmWA","sentiment":"neu","source":"<a href=\"http://twitter.com/download/android\" rel=\"nofollow\">Twitter for Android</a>","create_at":"Tue Dec 20 10:59:24 +0000 2022"},{"tweet_id":"1605149432642940928","screen_name":"MoonBirds15","user_name":"MoonBirds 📊","full_text":"Swing 🚥\n\n$HNT 🟡 $33.75\n$CELO 🟢 $4.06\n$OMG 🟡 $5.91\n$DASH 🟡 $127.20\n$gala $ETH\nhttps://t.co/CuKj1XsHDT\n\n$BTC $ETH $DOGE $SOL $XRP $BNB  $LTC  $MATIC $ADA $LINK $LUNC $DOT $ALGO $SHIB $USDC $USDT $SNM $BEAM $MAGIC $BNX $POLYX $CTXC $YFIl https://t.co/tmVCGp0WmY","sentiment":"neu","source":"<a href=\"http://twitter.com/download/android\" rel=\"nofollow\">Twitter for Android</a>","create_at":"Tue Dec 20 10:33:41 +0000 2022"},{"tweet_id":"1605104358470737920","screen_name":"peraci07","user_name":"süleyman peraçi","full_text":"$vib 0.45$ 🚀👍🌕❤\n\n@elonmusk @TheMoonCarl \n$nmr $btcst $doge $dc $nebl $bond $wtc $vgx $alpha $wnxm $ssv $snm  $unfi $perl  $firo $gal $amb $anc $wtc $loom $qlc $phb $anc\n$eth $btc  $shib\n$LUNC $LUNA $USTC $ETH $LINK $NEO $DASH $DOGE $MINA $uft  #kripto https://t.co/GMUozReoyB","sentiment":"neu","source":"<a href=\"http://twitter.com/download/android\" rel=\"nofollow\">Twitter for Android</a>","create_at":"Tue Dec 20 07:34:35 +0000 2022"},{"tweet_id":"1605083116313669632","screen_name":"LeBronJ19571083","user_name":"LeBron James 📈","full_text":"Swing 🚥\n\n$HNT 🟡 $33.75\n$CELO 🟢 $4.06\n$OMG 🟡 $5.91\n$DASH 🟡 $127.20\n$gala $ETH\nhttps://t.co/VM0N8POW4w\n\n$BTC $ETH $DOGE $SOL $XRP $BNB  $LTC  $MATIC $ADA $LINK $LUNC $DOT $ALGO $SHIB $USDC $USDT $SNM $BEAM $MAGIC $BNX $POLYX $CTXC $YFII https://t.co/WAqBOF5ieG","sentiment":"neu","source":"<a href=\"http://twitter.com/download/android\" rel=\"nofollow\">Twitter for Android</a>","create_at":"Tue Dec 20 06:10:10 +0000 2022"},{"tweet_id":"1605081790150225920","screen_name":"KingsMa06664790","user_name":"King","full_text":"TOP 10 #TVL ON BINANCE SMART CHAI\nhttps://t.co/gtjV0hzdds\n\n$BTC $ETH $DOGE $SOL $XRP $BNB  $LTC  $MATIC $ADA $LINK $LUNC $DOT $ALGO $SHIB $USDC $USDT $SNM $BEAM $MAGIC $BNX $POLYX $CTXC $YFII https://t.co/hZr6z5aQti","sentiment":"neu","source":"<a href=\"http://twitter.com/download/android\" rel=\"nofollow\">Twitter for Android</a>","create_at":"Tue Dec 20 06:04:54 +0000 2022"},{"tweet_id":"1605077453135024129","screen_name":"MoonBirds15","user_name":"MoonBirds 📊","full_text":"Profitable Crypto Trading Group\n➡ https://t.co/CuKj1XsHDT\n\n$BTC $ETH $DOGE $SOL $XRP $BNB  $LTC  $MATIC $ADA $LINK $LUNC $DOT $ALGO $SHIB $USDC $USDT $SNM $BEAM $MAGIC $BNX $POLYX $CTXC $YFII https://t.co/2WST2gMlnc","sentiment":"neu","source":"<a href=\"http://twitter.com/download/android\" rel=\"nofollow\">Twitter for Android</a>","create_at":"Tue Dec 20 05:47:40 +0000 2022"},{"tweet_id":"1605073445997674496","screen_name":"Miketys93226732","user_name":"Mike tyson 📈","full_text":"Profitable Crypto Trading Group\nhttps://t.co/n1dj0dIWrk\n\n$BTC $ETH $DOGE $SOL $XRP $BNB  $LTC  $MATIC $ADA $LINK $LUNC $DOT $ALGO $SHIB $USDC $USDT $SNM $BEAM $MAGIC $BNX $POLYX $CTXC $YFII https://t.co/pDIAnd41Nq","sentiment":"neu","source":"<a href=\"http://twitter.com/download/android\" rel=\"nofollow\">Twitter for Android</a>","create_at":"Tue Dec 20 05:31:45 +0000 2022"},{"tweet_id":"1605072005120036864","screen_name":"Miketys93226732","user_name":"Mike tyson 📈","full_text":"TOP 10 #TVL ON BINANCE SMART CHAI\nhttps://t.co/n1dj0dIWrk\n\n$BTC $ETH $DOGE $SOL $XRP $BNB  $LTC  $MATIC $ADA $LINK $LUNC $DOT $ALGO $SHIB $USDC $USDT $SNM $BEAM $MAGIC $BNX $POLYX $CTXC $YFII https://t.co/oD8WU5QZvc","sentiment":"neu","source":"<a href=\"http://twitter.com/download/android\" rel=\"nofollow\">Twitter for Android</a>","create_at":"Tue Dec 20 05:26:01 +0000 2022"},{"tweet_id":"1605047893060100096","screen_name":"Dominic42422840","user_name":"Dominic Murphy📈","full_text":"Swing 🚥\n\n$HNT 🟡 $33.75\n$CELO 🟢 $4.06\n$OMG 🟡 $5.91\n$DASH 🟡 $127.20\n$gala $ETH\nhttps://t.co/izlO7iFH36\n\n$BTC $ETH $DOGE $SOL $XRP $BNB  $LTC  $MATIC $ADA $LINK $LUNC $DOT $ALGO $SHIB $USDC $USDT $SNM $BEAM $MAGIC $BNX $POLYX $CTXC $YFII https://t.co/DDAO0Q1XZw","sentiment":"neu","source":"<a href=\"http://twitter.com/download/android\" rel=\"nofollow\">Twitter for Android</a>","create_at":"Tue Dec 20 03:50:12 +0000 2022"}]
