[{"tweet_id":"1593035146487222272","screen_name":"DelestreKatelyn","user_name":"Katelyn Delestre","full_text":"$aspi #aspi https://t.co/PjnZB9cQ8P","sentiment":"neu","source":"<a href=\"https://mobile.twitter.com\" rel=\"nofollow\">Twitter Web App</a>","create_at":"Thu Nov 17 00:15:50 +0000 2022"},{"tweet_id":"1592913360387215360","screen_name":"JoshuaW45498715","user_name":"Joshua WIlliams","full_text":"$ASPI 😢😢😢","sentiment":"neu","source":"<a href=\"https://stocktwits.com\" rel=\"nofollow\">StockTwits Web</a>","create_at":"Wed Nov 16 16:11:54 +0000 2022"}]
