[{"tweet_id":"1607881638100213765","screen_name":"Bolanet","user_name":"Bola","full_text":"Premier League bocorkan MU bakal rekrut striker asal Portugal?\nhttps://t.co/oJHd1sE3F0","sentiment":"neg","source":"<a href=\"https://about.twitter.com/products/tweetdeck\" rel=\"nofollow\">TweetDeck</a>","create_at":"Tue Dec 27 23:30:30 +0000 2022"},{"tweet_id":"1607880254042808322","screen_name":"Bolanet","user_name":"Bola","full_text":"Ekspektasi penggemar Newcastle meningkat, Eddi Howe coba realistis.\nhttps://t.co/S9eYv07d4W","sentiment":"pos","source":"<a href=\"https://about.twitter.com/products/tweetdeck\" rel=\"nofollow\">TweetDeck</a>","create_at":"Tue Dec 27 23:25:00 +0000 2022"},{"tweet_id":"1607880044122361857","screen_name":"Mrizkirahmadi21","user_name":"Muhammad Rizki Rahmadi","full_text":"@Bolanet Selebrasi menjijikkan,sama kayak ekspresi mukanya","sentiment":"neg","source":"<a href=\"http://twitter.com/download/android\" rel=\"nofollow\">Twitter for Android</a>","create_at":"Tue Dec 27 23:24:10 +0000 2022"},{"tweet_id":"1607879033026674688","screen_name":"hadioismailo","user_name":"Mailo","full_text":"@Bolanet Ingat belum juara lho","sentiment":"pos","source":"<a href=\"http://twitter.com/download/android\" rel=\"nofollow\">Twitter for Android</a>","create_at":"Tue Dec 27 23:20:09 +0000 2022"},{"tweet_id":"1607878995801956352","screen_name":"Bolanet","user_name":"Bola","full_text":"Tak perlu cemas Gabriel Jesus cedera, Arsenal masih punya Eddie Nketiah!\nhttps://t.co/N9hipmqVg3","sentiment":"neg","source":"<a href=\"https://about.twitter.com/products/tweetdeck\" rel=\"nofollow\">TweetDeck</a>","create_at":"Tue Dec 27 23:20:00 +0000 2022"},{"tweet_id":"1607877863339958273","screen_name":"Bolanet","user_name":"Bola","full_text":"Terlalu ribet, Liverpool mundur dari perburuan Jude Bellingham.\nhttps://t.co/Gw1DeyqNDM","sentiment":"neg","source":"<a href=\"https://about.twitter.com/products/tweetdeck\" rel=\"nofollow\">TweetDeck</a>","create_at":"Tue Dec 27 23:15:30 +0000 2022"},{"tweet_id":"1607876479441936384","screen_name":"Bolanet","user_name":"Bola","full_text":"Saddil Ramdani tentukan masa depan usai Piala AFF 2022, bisa bertahan atau merantau ke Eropa.\nhttps://t.co/la8X9LOSWv","sentiment":"neu","source":"<a href=\"https://about.twitter.com/products/tweetdeck\" rel=\"nofollow\">TweetDeck</a>","create_at":"Tue Dec 27 23:10:00 +0000 2022"},{"tweet_id":"1607875221167431680","screen_name":"Bolanet","user_name":"Bola","full_text":"De Bruyne yakin Haaland bakal lewati rekor gol milik Lionel Messi dan Cristiano Ronaldo!\nhttps://t.co/ak3XQu1n98","sentiment":"neg","source":"<a href=\"https://about.twitter.com/products/tweetdeck\" rel=\"nofollow\">TweetDeck</a>","create_at":"Tue Dec 27 23:05:00 +0000 2022"},{"tweet_id":"1607874089179381764","screen_name":"Bolanet","user_name":"Bola","full_text":"Jika sukses bungkam Thailand, Timnas Indonesia bakal diguyur bonus menggiurkan!\nhttps://t.co/rlyF9yTiqB","sentiment":"pos","source":"<a href=\"https://about.twitter.com/products/tweetdeck\" rel=\"nofollow\">TweetDeck</a>","create_at":"Tue Dec 27 23:00:30 +0000 2022"},{"tweet_id":"1607872830229680136","screen_name":"Bolanet","user_name":"Bola","full_text":"Termasuk Haaland, Deretan Pemain dengan Nilai Transfer Termahal di tahun 2022!\nhttps://t.co/bkD5e3SUAC","sentiment":"neu","source":"<a href=\"https://about.twitter.com/products/tweetdeck\" rel=\"nofollow\">TweetDeck</a>","create_at":"Tue Dec 27 22:55:30 +0000 2022"},{"tweet_id":"1607872788957728768","screen_name":"Bolanet","user_name":"Bola","full_text":"Buang-buang peluang saat lawan Aston Villa, Nunez dapat pembelaan dari Klopp.\nhttps://t.co/GOlHS7vN66","sentiment":"neu","source":"<a href=\"https://about.twitter.com/products/tweetdeck\" rel=\"nofollow\">TweetDeck</a>","create_at":"Tue Dec 27 22:55:20 +0000 2022"},{"tweet_id":"1607872579557289984","screen_name":"Bolanet","user_name":"Bola","full_text":"Bukan Ronaldo, Eks Pelatih Real Madrid ini lebih pilih Messi sebagai GOAT!\nhttps://t.co/ZBXSannOgX","sentiment":"neu","source":"<a href=\"https://about.twitter.com/products/tweetdeck\" rel=\"nofollow\">TweetDeck</a>","create_at":"Tue Dec 27 22:54:30 +0000 2022"},{"tweet_id":"1607871446474231808","screen_name":"Bolanet","user_name":"Bola","full_text":"Tiket Laga Timnas Indonesia vs Thailand belum terjual habis, yuk disikat!\nhttps://t.co/PUFaOux7oT","sentiment":"neg","source":"<a href=\"https://about.twitter.com/products/tweetdeck\" rel=\"nofollow\">TweetDeck</a>","create_at":"Tue Dec 27 22:50:00 +0000 2022"},{"tweet_id":"1607870187734274050","screen_name":"Bolanet","user_name":"Bola","full_text":"Legenda Prancis ini kecam selebrasi Emi Martinez di Piala Dunia 2022!\nhttps://t.co/Mdf3tkAXkg","sentiment":"neu","source":"<a href=\"https://about.twitter.com/products/tweetdeck\" rel=\"nofollow\">TweetDeck</a>","create_at":"Tue Dec 27 22:45:00 +0000 2022"},{"tweet_id":"1607868929669480450","screen_name":"Bolanet","user_name":"Bola","full_text":"Oleh-oleh Timnas Indonesia dari Malaysia: Kesasar hingga harus antre imigrasi!\nhttps://t.co/1Mv10ovWKu","sentiment":"neu","source":"<a href=\"https://about.twitter.com/products/tweetdeck\" rel=\"nofollow\">TweetDeck</a>","create_at":"Tue Dec 27 22:40:00 +0000 2022"},{"tweet_id":"1607867671592243200","screen_name":"Bolanet","user_name":"Bola","full_text":"Ini faktor kunci Liverpool kalahkan MU dalam perburuan Cody Gakpo!\nhttps://t.co/jFSE6hbZTE","sentiment":"neu","source":"<a href=\"https://about.twitter.com/products/tweetdeck\" rel=\"nofollow\">TweetDeck</a>","create_at":"Tue Dec 27 22:35:00 +0000 2022"},{"tweet_id":"1607864501130657792","screen_name":"Hakim_Rachman","user_name":"Hakim Rachman","full_text":"@Bolanet Titisan dr suka ngambeknya, soknya atau bijimana?","sentiment":"neu","source":"<a href=\"http://twitter.com/download/android\" rel=\"nofollow\">Twitter for Android</a>","create_at":"Tue Dec 27 22:22:24 +0000 2022"},{"tweet_id":"1607861380048195585","screen_name":"Bolanet","user_name":"Bola","full_text":"Begini Format masa depan Liverpool: 4-3-3 usang, ngeri setelah Gakpo bergabung!\nhttps://t.co/DiMdnBdezK","sentiment":"neg","source":"<a href=\"https://about.twitter.com/products/tweetdeck\" rel=\"nofollow\">TweetDeck</a>","create_at":"Tue Dec 27 22:10:00 +0000 2022"},{"tweet_id":"1607860677590548480","screen_name":"Bolanet","user_name":"Bola","full_text":"Begini nasib Legenda Jepang, Shunsuke Nakamura saat ini!\nhttps://t.co/t74hScC9uC","sentiment":"pos","source":"<a href=\"https://about.twitter.com/products/tweetdeck\" rel=\"nofollow\">TweetDeck</a>","create_at":"Tue Dec 27 22:07:12 +0000 2022"},{"tweet_id":"1607856196853153793","screen_name":"Bolanet","user_name":"Bola","full_text":"#LiveBolanet 87' GGGGOOOOOOOLLLLLLL! Fred buat MU semakin menjauh dari Nottingham Forest! #ManchesterUnited #NottinghamForest\n\nMan United 3-0 Nott Forest","sentiment":"neu","source":"<a href=\"https://www.hootsuite.com\" rel=\"nofollow\">Hootsuite Inc.</a>","create_at":"Tue Dec 27 21:49:24 +0000 2022"},{"tweet_id":"1607847729425747969","screen_name":"Bolanet","user_name":"Bola","full_text":"#LiveBolanet 55' Antony gagal memanfaatkan peluang emas setelah tembakannya dari jarak dekat masih mampu dihalau Hennessey! #ManchesterUnited #NottinghamForest\n\nMan United 2-0 Nott Forest","sentiment":"pos","source":"<a href=\"https://www.hootsuite.com\" rel=\"nofollow\">Hootsuite Inc.</a>","create_at":"Tue Dec 27 21:15:45 +0000 2022"},{"tweet_id":"1607844947901796352","screen_name":"Bolanet","user_name":"Bola","full_text":"#LiveBolanet 46' PPPRRRIIITTT Peluit tanda babak kedua sudah dimulai! #ManchesterUnited #NottinghamForest\n\nMan United 2-0 Nott Forest","sentiment":"neu","source":"<a href=\"https://www.hootsuite.com\" rel=\"nofollow\">Hootsuite Inc.</a>","create_at":"Tue Dec 27 21:04:42 +0000 2022"},{"tweet_id":"1607843782187270144","screen_name":"Bolanet","user_name":"Bola","full_text":"Arsene Wenger pilih waktu yang tepat untuk nonton Arsenal!\nhttps://t.co/hgFJlBH6IZ","sentiment":"pos","source":"<a href=\"https://about.twitter.com/products/tweetdeck\" rel=\"nofollow\">TweetDeck</a>","create_at":"Tue Dec 27 21:00:04 +0000 2022"},{"tweet_id":"1607842090070966278","screen_name":"Bolanet","user_name":"Bola","full_text":"Nunez bikin 4 tembakan tepat sasaran namun tetap 0 gol!\nhttps://t.co/GUsHoSvgl6","sentiment":"pos","source":"<a href=\"https://about.twitter.com/products/tweetdeck\" rel=\"nofollow\">TweetDeck</a>","create_at":"Tue Dec 27 20:53:21 +0000 2022"},{"tweet_id":"1607841291563319296","screen_name":"Bolanet","user_name":"Bola","full_text":"#LiveBolanet HT: Man United 2-0 Nott Forest (19'Rashford, 23'Martial) | Possessions: 70%-30% | Shots: 6-2 | Corners: 2-3\n.\nSetan Merah tampil dominan di babak pertama. https://t.co/JEDUG2Oj57","sentiment":"neu","source":"<a href=\"https://www.hootsuite.com\" rel=\"nofollow\">Hootsuite Inc.</a>","create_at":"Tue Dec 27 20:50:10 +0000 2022"},{"tweet_id":"1607840179183566849","screen_name":"Bolanet","user_name":"Bola","full_text":"#LiveBolanet 43' Setelah mengecek VAR, gol Forest yang dicetak oleh Yates dinyatakan tidak sah setelah bola menyentuh Boly yang berada dalam posisi offside! #ManchesterUnited #NottinghamForest\n\nMan United 2-0 Nott Forest","sentiment":"neg","source":"<a href=\"https://www.hootsuite.com\" rel=\"nofollow\">Hootsuite Inc.</a>","create_at":"Tue Dec 27 20:45:45 +0000 2022"},{"tweet_id":"1607839531302293505","screen_name":"Kabar_CHELSIB","user_name":"Kabar CHELSEA PERSIB","full_text":"Chelsea Akhirnya Menang Lagi! Saksikan Performa Apik The Blues Saat Sikat Bournemouth https://t.co/6rowRSRcqn (via @Bolanet) https://t.co/mV47ILGPg1","sentiment":"pos","source":"<a href=\"https://dlvrit.com/\" rel=\"nofollow\">dlvr.it</a>","create_at":"Tue Dec 27 20:43:11 +0000 2022"},{"tweet_id":"1607836215826341890","screen_name":"Bolanet","user_name":"Bola","full_text":"Haram hukumnya buat Timnas Indonesia gugup sebelum lawan Thailand!\nhttps://t.co/l3KrD8Ji8F","sentiment":"neg","source":"<a href=\"https://about.twitter.com/products/tweetdeck\" rel=\"nofollow\">TweetDeck</a>","create_at":"Tue Dec 27 20:30:00 +0000 2022"},{"tweet_id":"1607834828078030850","screen_name":"Bolanet","user_name":"Bola","full_text":"#LiveBolanet 23' GGGGOOOOOOOLLLLLLL! Martial berhasil selesaikan umpan Rashford dengan tendangan mendatar yang tak mampu dibendung Hennessey! #ManchesterUnited #NottinghamForest\n\nMan United 2-0 Nott Forest","sentiment":"neg","source":"<a href=\"https://www.hootsuite.com\" rel=\"nofollow\">Hootsuite Inc.</a>","create_at":"Tue Dec 27 20:24:29 +0000 2022"},{"tweet_id":"1607834010155384833","screen_name":"Bolanet","user_name":"Bola","full_text":"#LiveBolanet 19' GGGGOOOOOOOLLLLLLL! Eriksen kirimkan umpan mendatar dari sepak pojok yang diselesaikan dengan tendangan Rashford! #ManchesterUnited #NottinghamForest\n\nMan United 1-0 Nott Forest","sentiment":"neu","source":"<a href=\"https://about.twitter.com/products/tweetdeck\" rel=\"nofollow\">TweetDeck</a>","create_at":"Tue Dec 27 20:21:14 +0000 2022"},{"tweet_id":"1607832439291875328","screen_name":"Bolanet","user_name":"Bola","full_text":"'Titisan Cristiano Ronaldo' dirumorkan merapat ke Old Trafford.\nhttps://t.co/gz3YQv79tk","sentiment":"neu","source":"<a href=\"https://about.twitter.com/products/tweetdeck\" rel=\"nofollow\">TweetDeck</a>","create_at":"Tue Dec 27 20:15:00 +0000 2022"},{"tweet_id":"1607828854696976387","screen_name":"Bolanet","user_name":"Bola","full_text":"#LiveBolanet 0' Priiiiiit wasit meniup peluit tanda awal pertandingan babak pertama dimulai. Prediksi kalian Bolaneters? #Manchester United #NottinghamForest\n\nMan United 0-0 Nott Forest","sentiment":"neu","source":"<a href=\"https://www.hootsuite.com\" rel=\"nofollow\">Hootsuite Inc.</a>","create_at":"Tue Dec 27 20:00:45 +0000 2022"},{"tweet_id":"1607828796064911360","screen_name":"Bolanet","user_name":"Bola","full_text":"Misi Utama Ten Hag: Cari penerus Cristiano Ronaldo di MU!\nhttps://t.co/A87wLNn8Kv","sentiment":"neu","source":"<a href=\"https://about.twitter.com/products/tweetdeck\" rel=\"nofollow\">TweetDeck</a>","create_at":"Tue Dec 27 20:00:31 +0000 2022"},{"tweet_id":"1607824889645236225","screen_name":"Bolanet","user_name":"Bola","full_text":"Persimis masuk 3 besar, Klopp cukup dengan tiket lolos langsung ke Liga Champions.\nhttps://t.co/hT8VYkM7rT","sentiment":"neu","source":"<a href=\"https://about.twitter.com/products/tweetdeck\" rel=\"nofollow\">TweetDeck</a>","create_at":"Tue Dec 27 19:45:00 +0000 2022"},{"tweet_id":"1607821833637879808","screen_name":"Bolanet","user_name":"Bola","full_text":"#LiveBolanet Man United vs Nott Forest | Rabu, 28 Desember 2022 | pk 03.00 di SCTV dan Vidio. https://t.co/YodG0RbbpI","sentiment":"neu","source":"<a href=\"https://mobile.twitter.com\" rel=\"nofollow\">Twitter Web App</a>","create_at":"Tue Dec 27 19:32:51 +0000 2022"},{"tweet_id":"1607821242437931010","screen_name":"Bolanet","user_name":"Bola","full_text":"Begini jawaban Ten Hag terkait masa depan Dean Henderson di MU.\nhttps://t.co/Vuura8W95Z","sentiment":"neu","source":"<a href=\"https://about.twitter.com/products/tweetdeck\" rel=\"nofollow\">TweetDeck</a>","create_at":"Tue Dec 27 19:30:30 +0000 2022"},{"tweet_id":"1607817339621314561","screen_name":"Bolanet","user_name":"Bola","full_text":"Chelsea jadi yang terdepan untuk rekrut Declan Rice.\nhttps://t.co/4Tn4kq8vtR","sentiment":"neu","source":"<a href=\"https://about.twitter.com/products/tweetdeck\" rel=\"nofollow\">TweetDeck</a>","create_at":"Tue Dec 27 19:15:00 +0000 2022"},{"tweet_id":"1607813568228892672","screen_name":"Bolanet","user_name":"Bola","full_text":"Bukan ketikung, MU memang biarkan Gakpo pergi ke Liverpool.\nhttps://t.co/Ag4gYJ8jmV","sentiment":"neu","source":"<a href=\"https://about.twitter.com/products/tweetdeck\" rel=\"nofollow\">TweetDeck</a>","create_at":"Tue Dec 27 19:00:01 +0000 2022"},{"tweet_id":"1607809790046097408","screen_name":"Bolanet","user_name":"Bola","full_text":"Pelatih dan Legenda Liverpool ini bela performa buruk Darwin Nunez.\nhttps://t.co/mTkJX4Xc4d","sentiment":"neg","source":"<a href=\"https://about.twitter.com/products/tweetdeck\" rel=\"nofollow\">TweetDeck</a>","create_at":"Tue Dec 27 18:45:00 +0000 2022"},{"tweet_id":"1607807557321592833","screen_name":"Bolanet","user_name":"Bola","full_text":"#LiveBolanet 46' PPPRRRIIITTT Peluit tanda babak kedua sudah dimulai! #Chelsea #Bournemouth\n\nChelsea 2-0 Bournemouth","sentiment":"neu","source":"<a href=\"https://www.hootsuite.com\" rel=\"nofollow\">Hootsuite Inc.</a>","create_at":"Tue Dec 27 18:36:07 +0000 2022"}]
